wikipls/__init__.py
wikipls/consts.py
wikipls/func/__init__.py
wikipls/func/data.py
wikipls/func/get.py
wikipls/func/utils.py
wikipls/type_obj.py
wikipls/wiki_obj.py
wikipls-0.0.1.dev18.dist-info/LICENSE
wikipls-0.0.1.dev18.dist-info/METADATA
wikipls-0.0.1.dev18.dist-info/WHEEL
wikipls-0.0.1.dev18.dist-info/RECORD
