Metadata-Version: 2.1
Name: wikipls
Version: 0.0.1.dev18
Summary: A package for requesting data from Wikipedia using the REST API.
Home-page: https://github.com/SpanishCat/py-wikipls
License: LPGL-2.1-or-later
Keywords: wikipedia, rest, wiki, scraping, api
Author: Yonathan Katz
Author-email: yoni.gimi@gmail.com
Requires-Python: >=3.9,<4.0
Classifier: Development Status :: 3 - Alpha
Classifier: Intended Audience :: Developers
Classifier: Intended Audience :: Information Technology
Classifier: Intended Audience :: Science/Research
Classifier: License :: Other/Proprietary License
Classifier: Operating System :: OS Independent
Classifier: Programming Language :: Python :: 3
Classifier: Programming Language :: Python :: 3.9
Classifier: Programming Language :: Python :: 3.10
Classifier: Programming Language :: Python :: 3.11
Classifier: Programming Language :: Python :: 3.12
Classifier: Programming Language :: Python :: 3.13
Classifier: Topic :: Software Development :: Build Tools
Classifier: Topic :: Software Development :: Libraries :: Python Modules
Requires-Dist: requests (>=2.25.0,<3.0.0)
Project-URL: Issues, https://github.com/SpanishCat/py-wikipls/issues
Project-URL: Repository, https://github.com/SpanishCat/py-wikipls
Project-URL: Sponsor, https://github.com/sponsors/SpanishCat
